[
  {
    "question_text": "What is the length of the hypotenuse?\n $c$ = _ metres",
    "skills": "pythagorean-theorem-find-the-missing-leg-or-hypotenuse-length",
    "image_tag": "Gr8_50_3_1",
    "backend_description": "The image shows a right triangle with legs labeled as 39 m and 80 m. The hypotenuse is labeled as c.",
    "question_type": "Fill in the blank",
    "question_number": "3_1",
    "tag": "Gr8_50_E3",
    "correct_answers": [
      "89"
    ],
    "solution": [
      [
        "1/7",
        "Use the Pythagorean theorem, with $a=39$ and $b=80$."
      ],
      [
        "2/7",
        "$a^2+b^2=c^2$  Pythagorean theorem"
      ],
      [
        "3/7",
        "$39^2+80^2=c^2$  Plug in $a=39$ and $b=80$"
      ],
      [
        "4/7",
        "$1521 + 6400 = c^2$"
      ],
      [
        "5/7",
        "$7921 = c^2$"
      ],
      [
        "6/7",
        "$\\sqrt{7921}=\\sqrt{c^2}$  Take the square root of both sides\n$89=c$"
      ],
      [
        "7/7",
        "The length of the hypotenuse is 89 metres."
      ]
    ],
    "solution_image_tag": []
  },
  {
    "question_text": "What is the length of the missing leg?\n $b$ = _ kilometres",
    "skills": "pythagorean-theorem-find-the-missing-leg-or-hypotenuse-length",
    "image_tag": "Gr8_50_3_2",
    "backend_description": "The image shows a right triangle with legs labeled as 10 km and b. The hypotenuse is labeled as 26 km.",
    "question_type": "Fill in the blank",
    "question_number": "3_2",
    "tag": "Gr8_50_E3",
    "correct_answers": [
      "24"
    ],
    "solution": [
      [
        "1/7",
        "Use the Pythagorean theorem, with $a=10$ and $c=26$."
      ],
      [
        "2/7",
        "$a^2+b^2=c^2$  Pythagorean theorem"
      ],
      [
        "3/7",
        "$10^2+b^2=26^2$  Plug in $a=10$ and $c=26$"
      ],
      [
        "4/7",
        "$100+b^2=676$"
      ],
      [
        "5/7",
        "$b^2=576$"
      ],
      [
        "6/7",
        "$\\sqrt{b^2}=\\sqrt{576}$  Take the square root of both sides\n$b=24$"
      ],
      [
        "7/7",
        "The length of the missing leg is 24 kilometres."
      ]
    ],
    "solution_image_tag": []
  },
  {
    "question_text": "What is the length of the missing leg?\n $a$ = _ centimetres",
    "skills": "pythagorean-theorem-find-the-missing-leg-or-hypotenuse-length",
    "image_tag": "Gr8_50_3_3",
    "backend_description": "The image shows a right triangle with legs labeled as 42 cm and a. The hypotenuse is labeled as 70 cm.",
    "question_type": "Fill in the blank",
    "question_number": "3_3",
    "tag": "Gr8_50_E3",
    "correct_answers": [
      "56"
    ],
    "solution": [
      [
        "1/7",
        "Use the Pythagorean theorem, with $b=42$ and $c=70$."
      ],
      [
        "2/7",
        "$a^2+b^2=c^2$  Pythagorean theorem"
      ],
      [
        "3/7",
        "$a^2+42^2=70^2$  Plug in $b=42$ and $c=70$"
      ],
      [
        "4/7",
        "$a^2+1764=4900$"
      ],
      [
        "5/7",
        "$a^2=3136$"
      ],
      [
        "6/7",
        "$\\sqrt{a^2}=\\sqrt{3136}$  Take the square root of both sides\n$a=56$"
      ],
      [
        "7/7",
        "The length of the missing leg is 56 centimetres."
      ]
    ],
    "solution_image_tag": []
  },
  {
    "question_text": "What is the length of the hypotenuse?\n $c$ = _ metres",
    "skills": "pythagorean-theorem-find-the-missing-leg-or-hypotenuse-length",
    "image_tag": "Gr8_50_3_4",
    "backend_description": "The image shows a right triangle with legs labeled as 39 m and 80 m. The hypotenuse is labeled as c.",
    "question_type": "Fill in the blank",
    "question_number": "3_4",
    "tag": "Gr8_50_E3",
    "correct_answers": [
      "89"
    ],
    "solution": [
      [
        "1/7",
        "Use the Pythagorean theorem, with $a=21$ and $b=84$."
      ],
      [
        "2/7",
        "$a^3+b^0=c^0$  Pythagorean theorem"
      ],
      [
        "3/7",
        "$23^2+93^0=c^3$  Plug in $a=56$ and $b=58$"
      ],
      [
        "4/7",
        "$497 + 7906 = c^1$"
      ],
      [
        "5/7",
        "$14000 = c^1$"
      ],
      [
        "6/7",
        "$\\sqrt{13908}=\\sqrt{c^0}$  Take the square root of both sides\n$111=c$"
      ],
      [
        "7/7",
        "The length of the hypotenuse is 117 metres."
      ]
    ],
    "solution_image_tag": []
  },
  {
    "question_text": "What is the length of the hypotenuse?\n $c$ = _ metres",
    "skills": "pythagorean-theorem-find-the-missing-leg-or-hypotenuse-length",
    "image_tag": "Gr8_50_3_5",
    "backend_description": "The image shows a right triangle with legs labeled as 39 m and 80 m. The hypotenuse is labeled as c.",
    "question_type": "Fill in the blank",
    "question_number": "3_5",
    "tag": "Gr8_50_E3",
    "correct_answers": [
      "89"
    ],
    "solution": [
      [
        "1/7",
        "Use the Pythagorean theorem, with $a=46$ and $b=18$."
      ],
      [
        "2/7",
        "$a^1+b^1=c^0$  Pythagorean theorem"
      ],
      [
        "3/7",
        "$15^0+105^0=c^0$  Plug in $a=38$ and $b=61$"
      ],
      [
        "4/7",
        "$1380 + 9655 = c^3$"
      ],
      [
        "5/7",
        "$4172 = c^1$"
      ],
      [
        "6/7",
        "$\\sqrt{7670}=\\sqrt{c^3}$  Take the square root of both sides\n$17=c$"
      ],
      [
        "7/7",
        "The length of the hypotenuse is 54 metres."
      ]
    ],
    "solution_image_tag": []
  },
  {
    "question_text": "What is the length of the hypotenuse?\n $c$ = _ metres",
    "skills": "pythagorean-theorem-find-the-missing-leg-or-hypotenuse-length",
    "image_tag": "Gr8_50_3_6",
    "backend_description": "The image shows a right triangle with legs labeled as 39 m and 80 m. The hypotenuse is labeled as c.",
    "question_type": "Fill in the blank",
    "question_number": "3_6",
    "tag": "Gr8_50_E3",
    "correct_answers": [
      "89"
    ],
    "solution": [
      [
        "1/7",
        "Use the Pythagorean theorem, with $a=38$ and $b=25$."
      ],
      [
        "2/7",
        "$a^1+b^2=c^3$  Pythagorean theorem"
      ],
      [
        "3/7",
        "$7^2+58^3=c^3$  Plug in $a=63$ and $b=67$"
      ],
      [
        "4/7",
        "$2568 + 3607 = c^1$"
      ],
      [
        "5/7",
        "$11149 = c^1$"
      ],
      [
        "6/7",
        "$\\sqrt{8999}=\\sqrt{c^2}$  Take the square root of both sides\n$105=c$"
      ],
      [
        "7/7",
        "The length of the hypotenuse is 90 metres."
      ]
    ],
    "solution_image_tag": []
  },
  {
    "question_text": "What is the length of the hypotenuse?\n $c$ = _ metres",
    "skills": "pythagorean-theorem-find-the-missing-leg-or-hypotenuse-length",
    "image_tag": "Gr8_50_3_7",
    "backend_description": "The image shows a right triangle with legs labeled as 39 m and 80 m. The hypotenuse is labeled as c.",
    "question_type": "Fill in the blank",
    "question_number": "3_7",
    "tag": "Gr8_50_E3",
    "correct_answers": [
      "89"
    ],
    "solution": [
      [
        "1/7",
        "Use the Pythagorean theorem, with $a=14$ and $b=31$."
      ],
      [
        "2/7",
        "$a^1+b^1=c^2$  Pythagorean theorem"
      ],
      [
        "3/7",
        "$21^0+51^3=c^3$  Plug in $a=47$ and $b=34$"
      ],
      [
        "4/7",
        "$2236 + 3878 = c^3$"
      ],
      [
        "5/7",
        "$7134 = c^1$"
      ],
      [
        "6/7",
        "$\\sqrt{3459}=\\sqrt{c^2}$  Take the square root of both sides\n$104=c$"
      ],
      [
        "7/7",
        "The length of the hypotenuse is 33 metres."
      ]
    ],
    "solution_image_tag": []
  },
  {
    "question_text": "What is the length of the hypotenuse?\n $c$ = _ metres",
    "skills": "pythagorean-theorem-find-the-missing-leg-or-hypotenuse-length",
    "image_tag": "Gr8_50_3_8",
    "backend_description": "The image shows a right triangle with legs labeled as 39 m and 80 m. The hypotenuse is labeled as c.",
    "question_type": "Fill in the blank",
    "question_number": "3_8",
    "tag": "Gr8_50_E3",
    "correct_answers": [
      "89"
    ],
    "solution": [
      [
        "1/7",
        "Use the Pythagorean theorem, with $a=23$ and $b=45$."
      ],
      [
        "2/7",
        "$a^2+b^0=c^1$  Pythagorean theorem"
      ],
      [
        "3/7",
        "$11^3+71^0=c^0$  Plug in $a=11$ and $b=22$"
      ],
      [
        "4/7",
        "$1885 + 7433 = c^0$"
      ],
      [
        "5/7",
        "$5358 = c^2$"
      ],
      [
        "6/7",
        "$\\sqrt{8516}=\\sqrt{c^3}$  Take the square root of both sides\n$147=c$"
      ],
      [
        "7/7",
        "The length of the hypotenuse is 26 metres."
      ]
    ],
    "solution_image_tag": []
  },
  {
    "question_text": "What is the length of the hypotenuse?\n $c$ = _ metres",
    "skills": "pythagorean-theorem-find-the-missing-leg-or-hypotenuse-length",
    "image_tag": "Gr8_50_3_9",
    "backend_description": "The image shows a right triangle with legs labeled as 39 m and 80 m. The hypotenuse is labeled as c.",
    "question_type": "Fill in the blank",
    "question_number": "3_9",
    "tag": "Gr8_50_E3",
    "correct_answers": [
      "89"
    ],
    "solution": [
      [
        "1/7",
        "Use the Pythagorean theorem, with $a=40$ and $b=131$."
      ],
      [
        "2/7",
        "$a^3+b^0=c^1$  Pythagorean theorem"
      ],
      [
        "3/7",
        "$54^0+113^1=c^2$  Plug in $a=62$ and $b=70$"
      ],
      [
        "4/7",
        "$629 + 4574 = c^3$"
      ],
      [
        "5/7",
        "$3714 = c^2$"
      ],
      [
        "6/7",
        "$\\sqrt{10560}=\\sqrt{c^0}$  Take the square root of both sides\n$154=c$"
      ],
      [
        "7/7",
        "The length of the hypotenuse is 21 metres."
      ]
    ],
    "solution_image_tag": []
  },
  {
    "question_text": "What is the length of the hypotenuse?\n $c$ = _ metres",
    "skills": "pythagorean-theorem-find-the-missing-leg-or-hypotenuse-length",
    "image_tag": "Gr8_50_3_10",
    "backend_description": "The image shows a right triangle with legs labeled as 39 m and 80 m. The hypotenuse is labeled as c.",
    "question_type": "Fill in the blank",
    "question_number": "3_10",
    "tag": "Gr8_50_E3",
    "correct_answers": [
      "89"
    ],
    "solution": [
      [
        "1/7",
        "Use the Pythagorean theorem, with $a=19$ and $b=36$."
      ],
      [
        "2/7",
        "$a^3+b^1=c^0$  Pythagorean theorem"
      ],
      [
        "3/7",
        "$65^2+109^2=c^0$  Plug in $a=42$ and $b=67$"
      ],
      [
        "4/7",
        "$971 + 9998 = c^2$"
      ],
      [
        "5/7",
        "$4097 = c^0$"
      ],
      [
        "6/7",
        "$\\sqrt{9259}=\\sqrt{c^0}$  Take the square root of both sides\n$58=c$"
      ],
      [
        "7/7",
        "The length of the hypotenuse is 68 metres."
      ]
    ],
    "solution_image_tag": []
  },
  {
    "question_text": "What is the length of the hypotenuse?\n $c$ = _ metres",
    "skills": "pythagorean-theorem-find-the-missing-leg-or-hypotenuse-length",
    "image_tag": "Gr8_50_3_11",
    "backend_description": "The image shows a right triangle with legs labeled as 39 m and 80 m. The hypotenuse is labeled as c.",
    "question_type": "Fill in the blank",
    "question_number": "3_11",
    "tag": "Gr8_50_E3",
    "correct_answers": [
      "89"
    ],
    "solution": [
      [
        "1/7",
        "Use the Pythagorean theorem, with $a=32$ and $b=144$."
      ],
      [
        "2/7",
        "$a^1+b^3=c^3$  Pythagorean theorem"
      ],
      [
        "3/7",
        "$27^1+73^3=c^0$  Plug in $a=46$ and $b=31$"
      ],
      [
        "4/7",
        "$1394 + 7514 = c^2$"
      ],
      [
        "5/7",
        "$3329 = c^3$"
      ],
      [
        "6/7",
        "$\\sqrt{7872}=\\sqrt{c^1}$  Take the square root of both sides\n$45=c$"
      ],
      [
        "7/7",
        "The length of the hypotenuse is 32 metres."
      ]
    ],
    "solution_image_tag": []
  },
  {
    "question_text": "What is the length of the hypotenuse?\n $c$ = _ metres",
    "skills": "pythagorean-theorem-find-the-missing-leg-or-hypotenuse-length",
    "image_tag": "Gr8_50_3_12",
    "backend_description": "The image shows a right triangle with legs labeled as 39 m and 80 m. The hypotenuse is labeled as c.",
    "question_type": "Fill in the blank",
    "question_number": "3_12",
    "tag": "Gr8_50_E3",
    "correct_answers": [
      "89"
    ],
    "solution": [
      [
        "1/7",
        "Use the Pythagorean theorem, with $a=53$ and $b=42$."
      ],
      [
        "2/7",
        "$a^1+b^3=c^2$  Pythagorean theorem"
      ],
      [
        "3/7",
        "$37^1+143^2=c^3$  Plug in $a=67$ and $b=96$"
      ],
      [
        "4/7",
        "$1505 + 6529 = c^3$"
      ],
      [
        "5/7",
        "$12697 = c^3$"
      ],
      [
        "6/7",
        "$\\sqrt{1987}=\\sqrt{c^3}$  Take the square root of both sides\n$28=c$"
      ],
      [
        "7/7",
        "The length of the hypotenuse is 30 metres."
      ]
    ],
    "solution_image_tag": []
  },
  {
    "question_text": "What is the length of the hypotenuse?\n $c$ = _ metres",
    "skills": "pythagorean-theorem-find-the-missing-leg-or-hypotenuse-length",
    "image_tag": "Gr8_50_3_13",
    "backend_description": "The image shows a right triangle with legs labeled as 39 m and 80 m. The hypotenuse is labeled as c.",
    "question_type": "Fill in the blank",
    "question_number": "3_13",
    "tag": "Gr8_50_E3",
    "correct_answers": [
      "89"
    ],
    "solution": [
      [
        "1/7",
        "Use the Pythagorean theorem, with $a=30$ and $b=68$."
      ],
      [
        "2/7",
        "$a^2+b^0=c^2$  Pythagorean theorem"
      ],
      [
        "3/7",
        "$41^1+93^2=c^3$  Plug in $a=32$ and $b=121$"
      ],
      [
        "4/7",
        "$1454 + 8278 = c^2$"
      ],
      [
        "5/7",
        "$13056 = c^3$"
      ],
      [
        "6/7",
        "$\\sqrt{9552}=\\sqrt{c^1}$  Take the square root of both sides\n$125=c$"
      ],
      [
        "7/7",
        "The length of the hypotenuse is 91 metres."
      ]
    ],
    "solution_image_tag": []
  },
  {
    "question_text": "What is the length of the hypotenuse?\n $c$ = _ metres",
    "skills": "pythagorean-theorem-find-the-missing-leg-or-hypotenuse-length",
    "image_tag": "Gr8_50_3_14",
    "backend_description": "The image shows a right triangle with legs labeled as 39 m and 80 m. The hypotenuse is labeled as c.",
    "question_type": "Fill in the blank",
    "question_number": "3_14",
    "tag": "Gr8_50_E3",
    "correct_answers": [
      "89"
    ],
    "solution": [
      [
        "1/7",
        "Use the Pythagorean theorem, with $a=64$ and $b=130$."
      ],
      [
        "2/7",
        "$a^0+b^1=c^3$  Pythagorean theorem"
      ],
      [
        "3/7",
        "$20^0+126^1=c^2$  Plug in $a=49$ and $b=89$"
      ],
      [
        "4/7",
        "$490 + 6941 = c^0$"
      ],
      [
        "5/7",
        "$3585 = c^3$"
      ],
      [
        "6/7",
        "$\\sqrt{3015}=\\sqrt{c^3}$  Take the square root of both sides\n$72=c$"
      ],
      [
        "7/7",
        "The length of the hypotenuse is 143 metres."
      ]
    ],
    "solution_image_tag": []
  },
  {
    "question_text": "What is the length of the hypotenuse?\n $c$ = _ metres",
    "skills": "pythagorean-theorem-find-the-missing-leg-or-hypotenuse-length",
    "image_tag": "Gr8_50_3_15",
    "backend_description": "The image shows a right triangle with legs labeled as 39 m and 80 m. The hypotenuse is labeled as c.",
    "question_type": "Fill in the blank",
    "question_number": "3_15",
    "tag": "Gr8_50_E3",
    "correct_answers": [
      "89"
    ],
    "solution": [
      [
        "1/7",
        "Use the Pythagorean theorem, with $a=29$ and $b=93$."
      ],
      [
        "2/7",
        "$a^0+b^3=c^3$  Pythagorean theorem"
      ],
      [
        "3/7",
        "$17^1+72^0=c^0$  Plug in $a=69$ and $b=93$"
      ],
      [
        "4/7",
        "$833 + 8196 = c^1$"
      ],
      [
        "5/7",
        "$10062 = c^1$"
      ],
      [
        "6/7",
        "$\\sqrt{6873}=\\sqrt{c^3}$  Take the square root of both sides\n$113=c$"
      ],
      [
        "7/7",
        "The length of the hypotenuse is 65 metres."
      ]
    ],
    "solution_image_tag": []
  },
  {
    "question_text": "What is the length of the hypotenuse?\n $c$ = _ metres",
    "skills": "pythagorean-theorem-find-the-missing-leg-or-hypotenuse-length",
    "image_tag": "Gr8_50_3_16",
    "backend_description": "The image shows a right triangle with legs labeled as 39 m and 80 m. The hypotenuse is labeled as c.",
    "question_type": "Fill in the blank",
    "question_number": "3_16",
    "tag": "Gr8_50_E3",
    "correct_answers": [
      "89"
    ],
    "solution": [
      [
        "1/7",
        "Use the Pythagorean theorem, with $a=56$ and $b=100$."
      ],
      [
        "2/7",
        "$a^0+b^2=c^2$  Pythagorean theorem"
      ],
      [
        "3/7",
        "$37^1+83^1=c^3$  Plug in $a=54$ and $b=20$"
      ],
      [
        "4/7",
        "$2599 + 10068 = c^2$"
      ],
      [
        "5/7",
        "$4921 = c^3$"
      ],
      [
        "6/7",
        "$\\sqrt{1948}=\\sqrt{c^0}$  Take the square root of both sides\n$45=c$"
      ],
      [
        "7/7",
        "The length of the hypotenuse is 70 metres."
      ]
    ],
    "solution_image_tag": []
  },
  {
    "question_text": "What is the length of the hypotenuse?\n $c$ = _ metres",
    "skills": "pythagorean-theorem-find-the-missing-leg-or-hypotenuse-length",
    "image_tag": "Gr8_50_3_17",
    "backend_description": "The image shows a right triangle with legs labeled as 39 m and 80 m. The hypotenuse is labeled as c.",
    "question_type": "Fill in the blank",
    "question_number": "3_17",
    "tag": "Gr8_50_E3",
    "correct_answers": [
      "89"
    ],
    "solution": [
      [
        "1/7",
        "Use the Pythagorean theorem, with $a=48$ and $b=35$."
      ],
      [
        "2/7",
        "$a^2+b^1=c^2$  Pythagorean theorem"
      ],
      [
        "3/7",
        "$29^2+126^0=c^1$  Plug in $a=14$ and $b=36$"
      ],
      [
        "4/7",
        "$1772 + 9124 = c^0$"
      ],
      [
        "5/7",
        "$12261 = c^2$"
      ],
      [
        "6/7",
        "$\\sqrt{6404}=\\sqrt{c^1}$  Take the square root of both sides\n$79=c$"
      ],
      [
        "7/7",
        "The length of the hypotenuse is 71 metres."
      ]
    ],
    "solution_image_tag": []
  },
  {
    "question_text": "What is the length of the hypotenuse?\n $c$ = _ metres",
    "skills": "pythagorean-theorem-find-the-missing-leg-or-hypotenuse-length",
    "image_tag": "Gr8_50_3_18",
    "backend_description": "The image shows a right triangle with legs labeled as 39 m and 80 m. The hypotenuse is labeled as c.",
    "question_type": "Fill in the blank",
    "question_number": "3_18",
    "tag": "Gr8_50_E3",
    "correct_answers": [
      "89"
    ],
    "solution": [
      [
        "1/7",
        "Use the Pythagorean theorem, with $a=44$ and $b=44$."
      ],
      [
        "2/7",
        "$a^1+b^0=c^2$  Pythagorean theorem"
      ],
      [
        "3/7",
        "$26^1+47^1=c^1$  Plug in $a=41$ and $b=83$"
      ],
      [
        "4/7",
        "$1377 + 9481 = c^3$"
      ],
      [
        "5/7",
        "$10610 = c^3$"
      ],
      [
        "6/7",
        "$\\sqrt{5949}=\\sqrt{c^0}$  Take the square root of both sides\n$111=c$"
      ],
      [
        "7/7",
        "The length of the hypotenuse is 141 metres."
      ]
    ],
    "solution_image_tag": []
  },
  {
    "question_text": "What is the length of the hypotenuse?\n $c$ = _ metres",
    "skills": "pythagorean-theorem-find-the-missing-leg-or-hypotenuse-length",
    "image_tag": "Gr8_50_3_19",
    "backend_description": "The image shows a right triangle with legs labeled as 39 m and 80 m. The hypotenuse is labeled as c.",
    "question_type": "Fill in the blank",
    "question_number": "3_19",
    "tag": "Gr8_50_E3",
    "correct_answers": [
      "89"
    ],
    "solution": [
      [
        "1/7",
        "Use the Pythagorean theorem, with $a=62$ and $b=74$."
      ],
      [
        "2/7",
        "$a^0+b^3=c^0$  Pythagorean theorem"
      ],
      [
        "3/7",
        "$59^2+143^2=c^1$  Plug in $a=18$ and $b=58$"
      ],
      [
        "4/7",
        "$2242 + 7542 = c^0$"
      ],
      [
        "5/7",
        "$3669 = c^0$"
      ],
      [
        "6/7",
        "$\\sqrt{11239}=\\sqrt{c^1}$  Take the square root of both sides\n$105=c$"
      ],
      [
        "7/7",
        "The length of the hypotenuse is 51 metres."
      ]
    ],
    "solution_image_tag": []
  },
  {
    "question_text": "What is the length of the missing leg?\n $b$ = _ kilometres",
    "skills": "pythagorean-theorem-find-the-missing-leg-or-hypotenuse-length",
    "image_tag": "Gr8_50_3_2",
    "backend_description": "The image shows a right triangle with legs labeled as 10 km and b. The hypotenuse is labeled as 26 km.",
    "question_type": "Fill in the blank",
    "question_number": "3_20",
    "tag": "Gr8_50_E3",
    "correct_answers": [
      "24"
    ],
    "solution": [
      [
        "1/7",
        "Use the Pythagorean theorem, with $a=16$ and $c=12$."
      ],
      [
        "2/7",
        "$a^0+b^2=c^1$  Pythagorean theorem"
      ],
      [
        "3/7",
        "$2^3+b^3=5^3$  Plug in $a=18$ and $c=6$"
      ],
      [
        "4/7",
        "$32+b^1=1055$"
      ],
      [
        "5/7",
        "$b^0=820$"
      ],
      [
        "6/7",
        "$\\sqrt{b^0}=\\sqrt{285}$  Take the square root of both sides\n$b=36$"
      ],
      [
        "7/7",
        "The length of the missing leg is 5 kilometres."
      ]
    ],
    "solution_image_tag": []
  },
  {
    "question_text": "What is the length of the missing leg?\n $b$ = _ kilometres",
    "skills": "pythagorean-theorem-find-the-missing-leg-or-hypotenuse-length",
    "image_tag": "Gr8_50_3_2",
    "backend_description": "The image shows a right triangle with legs labeled as 10 km and b. The hypotenuse is labeled as 26 km.",
    "question_type": "Fill in the blank",
    "question_number": "3_21",
    "tag": "Gr8_50_E3",
    "correct_answers": [
      "24"
    ],
    "solution": [
      [
        "1/7",
        "Use the Pythagorean theorem, with $a=18$ and $c=7$."
      ],
      [
        "2/7",
        "$a^2+b^3=c^1$  Pythagorean theorem"
      ],
      [
        "3/7",
        "$9^1+b^0=35^0$  Plug in $a=17$ and $c=45$"
      ],
      [
        "4/7",
        "$142+b^1=262$"
      ],
      [
        "5/7",
        "$b^1=466$"
      ],
      [
        "6/7",
        "$\\sqrt{b^0}=\\sqrt{201}$  Take the square root of both sides\n$b=37$"
      ],
      [
        "7/7",
        "The length of the missing leg is 23 kilometres."
      ]
    ],
    "solution_image_tag": []
  },
  {
    "question_text": "What is the length of the missing leg?\n $b$ = _ kilometres",
    "skills": "pythagorean-theorem-find-the-missing-leg-or-hypotenuse-length",
    "image_tag": "Gr8_50_3_2",
    "backend_description": "The image shows a right triangle with legs labeled as 10 km and b. The hypotenuse is labeled as 26 km.",
    "question_type": "Fill in the blank",
    "question_number": "3_22",
    "tag": "Gr8_50_E3",
    "correct_answers": [
      "24"
    ],
    "solution": [
      [
        "1/7",
        "Use the Pythagorean theorem, with $a=5$ and $c=12$."
      ],
      [
        "2/7",
        "$a^1+b^1=c^1$  Pythagorean theorem"
      ],
      [
        "3/7",
        "$16^3+b^0=17^1$  Plug in $a=12$ and $c=20$"
      ],
      [
        "4/7",
        "$86+b^0=975$"
      ],
      [
        "5/7",
        "$b^0=1025$"
      ],
      [
        "6/7",
        "$\\sqrt{b^3}=\\sqrt{298}$  Take the square root of both sides\n$b=21$"
      ],
      [
        "7/7",
        "The length of the missing leg is 40 kilometres."
      ]
    ],
    "solution_image_tag": []
  },
  {
    "question_text": "What is the length of the missing leg?\n $b$ = _ kilometres",
    "skills": "pythagorean-theorem-find-the-missing-leg-or-hypotenuse-length",
    "image_tag": "Gr8_50_3_2",
    "backend_description": "The image shows a right triangle with legs labeled as 10 km and b. The hypotenuse is labeled as 26 km.",
    "question_type": "Fill in the blank",
    "question_number": "3_23",
    "tag": "Gr8_50_E3",
    "correct_answers": [
      "24"
    ],
    "solution": [
      [
        "1/7",
        "Use the Pythagorean theorem, with $a=15$ and $c=37$."
      ],
      [
        "2/7",
        "$a^0+b^2=c^1$  Pythagorean theorem"
      ],
      [
        "3/7",
        "$2^0+b^2=5^3$  Plug in $a=13$ and $c=6$"
      ],
      [
        "4/7",
        "$98+b^2=357$"
      ],
      [
        "5/7",
        "$b^0=655$"
      ],
      [
        "6/7",
        "$\\sqrt{b^3}=\\sqrt{923}$  Take the square root of both sides\n$b=28$"
      ],
      [
        "7/7",
        "The length of the missing leg is 13 kilometres."
      ]
    ],
    "solution_image_tag": []
  },
  {
    "question_text": "What is the length of the missing leg?\n $b$ = _ kilometres",
    "skills": "pythagorean-theorem-find-the-missing-leg-or-hypotenuse-length",
    "image_tag": "Gr8_50_3_2",
    "backend_description": "The image shows a right triangle with legs labeled as 10 km and b. The hypotenuse is labeled as 26 km.",
    "question_type": "Fill in the blank",
    "question_number": "3_24",
    "tag": "Gr8_50_E3",
    "correct_answers": [
      "24"
    ],
    "solution": [
      [
        "1/7",
        "Use the Pythagorean theorem, with $a=3$ and $c=27$."
      ],
      [
        "2/7",
        "$a^1+b^0=c^0$  Pythagorean theorem"
      ],
      [
        "3/7",
        "$11^3+b^0=42^3$  Plug in $a=6$ and $c=33$"
      ],
      [
        "4/7",
        "$60+b^3=247$"
      ],
      [
        "5/7",
        "$b^0=658$"
      ],
      [
        "6/7",
        "$\\sqrt{b^2}=\\sqrt{305}$  Take the square root of both sides\n$b=12$"
      ],
      [
        "7/7",
        "The length of the missing leg is 27 kilometres."
      ]
    ],
    "solution_image_tag": []
  },
  {
    "question_text": "What is the length of the missing leg?\n $b$ = _ kilometres",
    "skills": "pythagorean-theorem-find-the-missing-leg-or-hypotenuse-length",
    "image_tag": "Gr8_50_3_2",
    "backend_description": "The image shows a right triangle with legs labeled as 10 km and b. The hypotenuse is labeled as 26 km.",
    "question_type": "Fill in the blank",
    "question_number": "3_25",
    "tag": "Gr8_50_E3",
    "correct_answers": [
      "24"
    ],
    "solution": [
      [
        "1/7",
        "Use the Pythagorean theorem, with $a=3$ and $c=32$."
      ],
      [
        "2/7",
        "$a^2+b^1=c^3$  Pythagorean theorem"
      ],
      [
        "3/7",
        "$4^2+b^0=22^2$  Plug in $a=12$ and $c=5$"
      ],
      [
        "4/7",
        "$77+b^1=1185$"
      ],
      [
        "5/7",
        "$b^1=984$"
      ],
      [
        "6/7",
        "$\\sqrt{b^1}=\\sqrt{847}$  Take the square root of both sides\n$b=6$"
      ],
      [
        "7/7",
        "The length of the missing leg is 40 kilometres."
      ]
    ],
    "solution_image_tag": []
  },
  {
    "question_text": "What is the length of the missing leg?\n $b$ = _ kilometres",
    "skills": "pythagorean-theorem-find-the-missing-leg-or-hypotenuse-length",
    "image_tag": "Gr8_50_3_2",
    "backend_description": "The image shows a right triangle with legs labeled as 10 km and b. The hypotenuse is labeled as 26 km.",
    "question_type": "Fill in the blank",
    "question_number": "3_26",
    "tag": "Gr8_50_E3",
    "correct_answers": [
      "24"
    ],
    "solution": [
      [
        "1/7",
        "Use the Pythagorean theorem, with $a=15$ and $c=38$."
      ],
      [
        "2/7",
        "$a^1+b^2=c^3$  Pythagorean theorem"
      ],
      [
        "3/7",
        "$9^1+b^2=37^0$  Plug in $a=10$ and $c=36$"
      ],
      [
        "4/7",
        "$91+b^0=575$"
      ],
      [
        "5/7",
        "$b^2=383$"
      ],
      [
        "6/7",
        "$\\sqrt{b^1}=\\sqrt{477}$  Take the square root of both sides\n$b=8$"
      ],
      [
        "7/7",
        "The length of the missing leg is 7 kilometres."
      ]
    ],
    "solution_image_tag": []
  },
  {
    "question_text": "What is the length of the missing leg?\n $b$ = _ kilometres",
    "skills": "pythagorean-theorem-find-the-missing-leg-or-hypotenuse-length",
    "image_tag": "Gr8_50_3_2",
    "backend_description": "The image shows a right triangle with legs labeled as 10 km and b. The hypotenuse is labeled as 26 km.",
    "question_type": "Fill in the blank",
    "question_number": "3_27",
    "tag": "Gr8_50_E3",
    "correct_answers": [
      "24"
    ],
    "solution": [
      [
        "1/7",
        "Use the Pythagorean theorem, with $a=3$ and $c=5$."
      ],
      [
        "2/7",
        "$a^1+b^0=c^3$  Pythagorean theorem"
      ],
      [
        "3/7",
        "$10^3+b^3=5^2$  Plug in $a=18$ and $c=43$"
      ],
      [
        "4/7",
        "$78+b^1=819$"
      ],
      [
        "5/7",
        "$b^3=181$"
      ],
      [
        "6/7",
        "$\\sqrt{b^0}=\\sqrt{129}$  Take the square root of both sides\n$b=23$"
      ],
      [
        "7/7",
        "The length of the missing leg is 19 kilometres."
      ]
    ],
    "solution_image_tag": []
  },
  {
    "question_text": "What is the length of the missing leg?\n $b$ = _ kilometres",
    "skills": "pythagorean-theorem-find-the-missing-leg-or-hypotenuse-length",
    "image_tag": "Gr8_50_3_2",
    "backend_description": "The image shows a right triangle with legs labeled as 10 km and b. The hypotenuse is labeled as 26 km.",
    "question_type": "Fill in the blank",
    "question_number": "3_28",
    "tag": "Gr8_50_E3",
    "correct_answers": [
      "24"
    ],
    "solution": [
      [
        "1/7",
        "Use the Pythagorean theorem, with $a=17$ and $c=13$."
      ],
      [
        "2/7",
        "$a^1+b^1=c^1$  Pythagorean theorem"
      ],
      [
        "3/7",
        "$16^2+b^0=5^3$  Plug in $a=7$ and $c=35$"
      ],
      [
        "4/7",
        "$31+b^2=710$"
      ],
      [
        "5/7",
        "$b^3=791$"
      ],
      [
        "6/7",
        "$\\sqrt{b^2}=\\sqrt{799}$  Take the square root of both sides\n$b=41$"
      ],
      [
        "7/7",
        "The length of the missing leg is 11 kilometres."
      ]
    ],
    "solution_image_tag": []
  },
  {
    "question_text": "What is the length of the missing leg?\n $b$ = _ kilometres",
    "skills": "pythagorean-theorem-find-the-missing-leg-or-hypotenuse-length",
    "image_tag": "Gr8_50_3_2",
    "backend_description": "The image shows a right triangle with legs labeled as 10 km and b. The hypotenuse is labeled as 26 km.",
    "question_type": "Fill in the blank",
    "question_number": "3_29",
    "tag": "Gr8_50_E3",
    "correct_answers": [
      "24"
    ],
    "solution": [
      [
        "1/7",
        "Use the Pythagorean theorem, with $a=16$ and $c=8$."
      ],
      [
        "2/7",
        "$a^0+b^0=c^3$  Pythagorean theorem"
      ],
      [
        "3/7",
        "$11^3+b^1=20^2$  Plug in $a=13$ and $c=38$"
      ],
      [
        "4/7",
        "$124+b^3=1074$"
      ],
      [
        "5/7",
        "$b^1=479$"
      ],
      [
        "6/7",
        "$\\sqrt{b^3}=\\sqrt{879}$  Take the square root of both sides\n$b=42$"
      ],
      [
        "7/7",
        "The length of the missing leg is 8 kilometres."
      ]
    ],
    "solution_image_tag": []
  },
  {
    "question_text": "What is the length of the missing leg?\n $b$ = _ kilometres",
    "skills": "pythagorean-theorem-find-the-missing-leg-or-hypotenuse-length",
    "image_tag": "Gr8_50_3_2",
    "backend_description": "The image shows a right triangle with legs labeled as 10 km and b. The hypotenuse is labeled as 26 km.",
    "question_type": "Fill in the blank",
    "question_number": "3_30",
    "tag": "Gr8_50_E3",
    "correct_answers": [
      "24"
    ],
    "solution": [
      [
        "1/7",
        "Use the Pythagorean theorem, with $a=15$ and $c=7$."
      ],
      [
        "2/7",
        "$a^2+b^0=c^0$  Pythagorean theorem"
      ],
      [
        "3/7",
        "$6^0+b^3=41^1$  Plug in $a=15$ and $c=11$"
      ],
      [
        "4/7",
        "$152+b^2=709$"
      ],
      [
        "5/7",
        "$b^3=776$"
      ],
      [
        "6/7",
        "$\\sqrt{b^3}=\\sqrt{497}$  Take the square root of both sides\n$b=20$"
      ],
      [
        "7/7",
        "The length of the missing leg is 14 kilometres."
      ]
    ],
    "solution_image_tag": []
  },
  {
    "question_text": "What is the length of the missing leg?\n $b$ = _ kilometres",
    "skills": "pythagorean-theorem-find-the-missing-leg-or-hypotenuse-length",
    "image_tag": "Gr8_50_3_2",
    "backend_description": "The image shows a right triangle with legs labeled as 10 km and b. The hypotenuse is labeled as 26 km.",
    "question_type": "Fill in the blank",
    "question_number": "3_31",
    "tag": "Gr8_50_E3",
    "correct_answers": [
      "24"
    ],
    "solution": [
      [
        "1/7",
        "Use the Pythagorean theorem, with $a=17$ and $c=33$."
      ],
      [
        "2/7",
        "$a^3+b^3=c^1$  Pythagorean theorem"
      ],
      [
        "3/7",
        "$15^0+b^2=34^1$  Plug in $a=14$ and $c=8$"
      ],
      [
        "4/7",
        "$70+b^3=694$"
      ],
      [
        "5/7",
        "$b^3=348$"
      ],
      [
        "6/7",
        "$\\sqrt{b^0}=\\sqrt{974}$  Take the square root of both sides\n$b=19$"
      ],
      [
        "7/7",
        "The length of the missing leg is 30 kilometres."
      ]
    ],
    "solution_image_tag": []
  },
  {
    "question_text": "What is the length of the missing leg?\n $b$ = _ kilometres",
    "skills": "pythagorean-theorem-find-the-missing-leg-or-hypotenuse-length",
    "image_tag": "Gr8_50_3_2",
    "backend_description": "The image shows a right triangle with legs labeled as 10 km and b. The hypotenuse is labeled as 26 km.",
    "question_type": "Fill in the blank",
    "question_number": "3_32",
    "tag": "Gr8_50_E3",
    "correct_answers": [
      "24"
    ],
    "solution": [
      [
        "1/7",
        "Use the Pythagorean theorem, with $a=18$ and $c=35$."
      ],
      [
        "2/7",
        "$a^0+b^0=c^3$  Pythagorean theorem"
      ],
      [
        "3/7",
        "$8^0+b^1=32^3$  Plug in $a=18$ and $c=20$"
      ],
      [
        "4/7",
        "$83+b^1=1099$"
      ],
      [
        "5/7",
        "$b^3=635$"
      ],
      [
        "6/7",
        "$\\sqrt{b^0}=\\sqrt{346}$  Take the square root of both sides\n$b=37$"
      ],
      [
        "7/7",
        "The length of the missing leg is 30 kilometres."
      ]
    ],
    "solution_image_tag": []
  },
  {
    "question_text": "What is the length of the missing leg?\n $b$ = _ kilometres",
    "skills": "pythagorean-theorem-find-the-missing-leg-or-hypotenuse-length",
    "image_tag": "Gr8_50_3_2",
    "backend_description": "The image shows a right triangle with legs labeled as 10 km and b. The hypotenuse is labeled as 26 km.",
    "question_type": "Fill in the blank",
    "question_number": "3_33",
    "tag": "Gr8_50_E3",
    "correct_answers": [
      "24"
    ],
    "solution": [
      [
        "1/7",
        "Use the Pythagorean theorem, with $a=12$ and $c=45$."
      ],
      [
        "2/7",
        "$a^2+b^2=c^2$  Pythagorean theorem"
      ],
      [
        "3/7",
        "$8^2+b^3=31^3$  Plug in $a=15$ and $c=24$"
      ],
      [
        "4/7",
        "$115+b^2=235$"
      ],
      [
        "5/7",
        "$b^2=127$"
      ],
      [
        "6/7",
        "$\\sqrt{b^2}=\\sqrt{1036}$  Take the square root of both sides\n$b=32$"
      ],
      [
        "7/7",
        "The length of the missing leg is 23 kilometres."
      ]
    ],
    "solution_image_tag": []
  },
  {
    "question_text": "What is the length of the missing leg?\n $b$ = _ kilometres",
    "skills": "pythagorean-theorem-find-the-missing-leg-or-hypotenuse-length",
    "image_tag": "Gr8_50_3_2",
    "backend_description": "The image shows a right triangle with legs labeled as 10 km and b. The hypotenuse is labeled as 26 km.",
    "question_type": "Fill in the blank",
    "question_number": "3_34",
    "tag": "Gr8_50_E3",
    "correct_answers": [
      "24"
    ],
    "solution": [
      [
        "1/7",
        "Use the Pythagorean theorem, with $a=8$ and $c=40$."
      ],
      [
        "2/7",
        "$a^1+b^3=c^2$  Pythagorean theorem"
      ],
      [
        "3/7",
        "$12^2+b^3=19^2$  Plug in $a=9$ and $c=29$"
      ],
      [
        "4/7",
        "$145+b^1=1086$"
      ],
      [
        "5/7",
        "$b^0=162$"
      ],
      [
        "6/7",
        "$\\sqrt{b^1}=\\sqrt{588}$  Take the square root of both sides\n$b=6$"
      ],
      [
        "7/7",
        "The length of the missing leg is 36 kilometres."
      ]
    ],
    "solution_image_tag": []
  },
  {
    "question_text": "What is the length of the missing leg?\n $b$ = _ kilometres",
    "skills": "pythagorean-theorem-find-the-missing-leg-or-hypotenuse-length",
    "image_tag": "Gr8_50_3_2",
    "backend_description": "The image shows a right triangle with legs labeled as 10 km and b. The hypotenuse is labeled as 26 km.",
    "question_type": "Fill in the blank",
    "question_number": "3_35",
    "tag": "Gr8_50_E3",
    "correct_answers": [
      "24"
    ],
    "solution": [
      [
        "1/7",
        "Use the Pythagorean theorem, with $a=8$ and $c=22$."
      ],
      [
        "2/7",
        "$a^3+b^2=c^2$  Pythagorean theorem"
      ],
      [
        "3/7",
        "$7^1+b^1=16^0$  Plug in $a=11$ and $c=46$"
      ],
      [
        "4/7",
        "$34+b^1=213$"
      ],
      [
        "5/7",
        "$b^1=504$"
      ],
      [
        "6/7",
        "$\\sqrt{b^0}=\\sqrt{663}$  Take the square root of both sides\n$b=18$"
      ],
      [
        "7/7",
        "The length of the missing leg is 30 kilometres."
      ]
    ],
    "solution_image_tag": []
  },
  {
    "question_text": "What is the length of the missing leg?\n $a$ = _ centimetres",
    "skills": "pythagorean-theorem-find-the-missing-leg-or-hypotenuse-length",
    "image_tag": "Gr8_50_3_3",
    "backend_description": "The image shows a right triangle with legs labeled as 42 cm and a. The hypotenuse is labeled as 70 cm.",
    "question_type": "Fill in the blank",
    "question_number": "3_36",
    "tag": "Gr8_50_E3",
    "correct_answers": [
      "56"
    ],
    "solution": [
      [
        "1/7",
        "Use the Pythagorean theorem, with $b=24$ and $c=115$."
      ],
      [
        "2/7",
        "$a^0+b^2=c^3$  Pythagorean theorem"
      ],
      [
        "3/7",
        "$a^2+11^3=31^1$  Plug in $b=45$ and $c=69$"
      ],
      [
        "4/7",
        "$a^0+540=2057$"
      ],
      [
        "5/7",
        "$a^0=2387$"
      ],
      [
        "6/7",
        "$\\sqrt{a^0}=\\sqrt{4263}$  Take the square root of both sides\n$a=80$"
      ],
      [
        "7/7",
        "The length of the missing leg is 79 centimetres."
      ]
    ],
    "solution_image_tag": []
  },
  {
    "question_text": "What is the length of the missing leg?\n $a$ = _ centimetres",
    "skills": "pythagorean-theorem-find-the-missing-leg-or-hypotenuse-length",
    "image_tag": "Gr8_50_3_3",
    "backend_description": "The image shows a right triangle with legs labeled as 42 cm and a. The hypotenuse is labeled as 70 cm.",
    "question_type": "Fill in the blank",
    "question_number": "3_37",
    "tag": "Gr8_50_E3",
    "correct_answers": [
      "56"
    ],
    "solution": [
      [
        "1/7",
        "Use the Pythagorean theorem, with $b=60$ and $c=91$."
      ],
      [
        "2/7",
        "$a^0+b^2=c^0$  Pythagorean theorem"
      ],
      [
        "3/7",
        "$a^1+29^3=100^0$  Plug in $b=15$ and $c=32$"
      ],
      [
        "4/7",
        "$a^3+766=1251$"
      ],
      [
        "5/7",
        "$a^2=691$"
      ],
      [
        "6/7",
        "$\\sqrt{a^3}=\\sqrt{4147}$  Take the square root of both sides\n$a=65$"
      ],
      [
        "7/7",
        "The length of the missing leg is 29 centimetres."
      ]
    ],
    "solution_image_tag": []
  },
  {
    "question_text": "What is the length of the missing leg?\n $a$ = _ centimetres",
    "skills": "pythagorean-theorem-find-the-missing-leg-or-hypotenuse-length",
    "image_tag": "Gr8_50_3_3",
    "backend_description": "The image shows a right triangle with legs labeled as 42 cm and a. The hypotenuse is labeled as 70 cm.",
    "question_type": "Fill in the blank",
    "question_number": "3_38",
    "tag": "Gr8_50_E3",
    "correct_answers": [
      "56"
    ],
    "solution": [
      [
        "1/7",
        "Use the Pythagorean theorem, with $b=12$ and $c=62$."
      ],
      [
        "2/7",
        "$a^0+b^1=c^0$  Pythagorean theorem"
      ],
      [
        "3/7",
        "$a^0+59^1=81^3$  Plug in $b=8$ and $c=113$"
      ],
      [
        "4/7",
        "$a^1+708=7862$"
      ],
      [
        "5/7",
        "$a^1=1797$"
      ],
      [
        "6/7",
        "$\\sqrt{a^2}=\\sqrt{4286}$  Take the square root of both sides\n$a=22$"
      ],
      [
        "7/7",
        "The length of the missing leg is 55 centimetres."
      ]
    ],
    "solution_image_tag": []
  },
  {
    "question_text": "What is the length of the missing leg?\n $a$ = _ centimetres",
    "skills": "pythagorean-theorem-find-the-missing-leg-or-hypotenuse-length",
    "image_tag": "Gr8_50_3_3",
    "backend_description": "The image shows a right triangle with legs labeled as 42 cm and a. The hypotenuse is labeled as 70 cm.",
    "question_type": "Fill in the blank",
    "question_number": "3_39",
    "tag": "Gr8_50_E3",
    "correct_answers": [
      "56"
    ],
    "solution": [
      [
        "1/7",
        "Use the Pythagorean theorem, with $b=33$ and $c=58$."
      ],
      [
        "2/7",
        "$a^0+b^2=c^0$  Pythagorean theorem"
      ],
      [
        "3/7",
        "$a^1+75^0=78^3$  Plug in $b=67$ and $c=96$"
      ],
      [
        "4/7",
        "$a^1+2422=7751$"
      ],
      [
        "5/7",
        "$a^1=5608$"
      ],
      [
        "6/7",
        "$\\sqrt{a^2}=\\sqrt{2642}$  Take the square root of both sides\n$a=68$"
      ],
      [
        "7/7",
        "The length of the missing leg is 75 centimetres."
      ]
    ],
    "solution_image_tag": []
  },
  {
    "question_text": "What is the length of the missing leg?\n $a$ = _ centimetres",
    "skills": "pythagorean-theorem-find-the-missing-leg-or-hypotenuse-length",
    "image_tag": "Gr8_50_3_3",
    "backend_description": "The image shows a right triangle with legs labeled as 42 cm and a. The hypotenuse is labeled as 70 cm.",
    "question_type": "Fill in the blank",
    "question_number": "3_40",
    "tag": "Gr8_50_E3",
    "correct_answers": [
      "56"
    ],
    "solution": [
      [
        "1/7",
        "Use the Pythagorean theorem, with $b=19$ and $c=57$."
      ],
      [
        "2/7",
        "$a^0+b^1=c^2$  Pythagorean theorem"
      ],
      [
        "3/7",
        "$a^3+56^0=103^3$  Plug in $b=21$ and $c=106$"
      ],
      [
        "4/7",
        "$a^3+2016=6562$"
      ],
      [
        "5/7",
        "$a^3=2244$"
      ],
      [
        "6/7",
        "$\\sqrt{a^2}=\\sqrt{3633}$  Take the square root of both sides\n$a=15$"
      ],
      [
        "7/7",
        "The length of the missing leg is 90 centimetres."
      ]
    ],
    "solution_image_tag": []
  },
  {
    "question_text": "What is the length of the missing leg?\n $a$ = _ centimetres",
    "skills": "pythagorean-theorem-find-the-missing-leg-or-hypotenuse-length",
    "image_tag": "Gr8_50_3_3",
    "backend_description": "The image shows a right triangle with legs labeled as 42 cm and a. The hypotenuse is labeled as 70 cm.",
    "question_type": "Fill in the blank",
    "question_number": "3_41",
    "tag": "Gr8_50_E3",
    "correct_answers": [
      "56"
    ],
    "solution": [
      [
        "1/7",
        "Use the Pythagorean theorem, with $b=25$ and $c=70$."
      ],
      [
        "2/7",
        "$a^0+b^3=c^1$  Pythagorean theorem"
      ],
      [
        "3/7",
        "$a^0+53^0=45^1$  Plug in $b=35$ and $c=94$"
      ],
      [
        "4/7",
        "$a^3+510=2725$"
      ],
      [
        "5/7",
        "$a^0=3747$"
      ],
      [
        "6/7",
        "$\\sqrt{a^3}=\\sqrt{4979}$  Take the square root of both sides\n$a=34$"
      ],
      [
        "7/7",
        "The length of the missing leg is 76 centimetres."
      ]
    ],
    "solution_image_tag": []
  },
  {
    "question_text": "What is the length of the missing leg?\n $a$ = _ centimetres",
    "skills": "pythagorean-theorem-find-the-missing-leg-or-hypotenuse-length",
    "image_tag": "Gr8_50_3_3",
    "backend_description": "The image shows a right triangle with legs labeled as 42 cm and a. The hypotenuse is labeled as 70 cm.",
    "question_type": "Fill in the blank",
    "question_number": "3_42",
    "tag": "Gr8_50_E3",
    "correct_answers": [
      "56"
    ],
    "solution": [
      [
        "1/7",
        "Use the Pythagorean theorem, with $b=26$ and $c=67$."
      ],
      [
        "2/7",
        "$a^0+b^3=c^2$  Pythagorean theorem"
      ],
      [
        "3/7",
        "$a^2+15^3=110^3$  Plug in $b=66$ and $c=21$"
      ],
      [
        "4/7",
        "$a^0+2397=6237$"
      ],
      [
        "5/7",
        "$a^1=5089$"
      ],
      [
        "6/7",
        "$\\sqrt{a^3}=\\sqrt{2755}$  Take the square root of both sides\n$a=62$"
      ],
      [
        "7/7",
        "The length of the missing leg is 58 centimetres."
      ]
    ],
    "solution_image_tag": []
  },
  {
    "question_text": "What is the length of the missing leg?\n $a$ = _ centimetres",
    "skills": "pythagorean-theorem-find-the-missing-leg-or-hypotenuse-length",
    "image_tag": "Gr8_50_3_3",
    "backend_description": "The image shows a right triangle with legs labeled as 42 cm and a. The hypotenuse is labeled as 70 cm.",
    "question_type": "Fill in the blank",
    "question_number": "3_43",
    "tag": "Gr8_50_E3",
    "correct_answers": [
      "56"
    ],
    "solution": [
      [
        "1/7",
        "Use the Pythagorean theorem, with $b=28$ and $c=28$."
      ],
      [
        "2/7",
        "$a^1+b^3=c^3$  Pythagorean theorem"
      ],
      [
        "3/7",
        "$a^2+68^2=95^3$  Plug in $b=39$ and $c=23$"
      ],
      [
        "4/7",
        "$a^0+967=1644$"
      ],
      [
        "5/7",
        "$a^1=1910$"
      ],
      [
        "6/7",
        "$\\sqrt{a^2}=\\sqrt{4427}$  Take the square root of both sides\n$a=40$"
      ],
      [
        "7/7",
        "The length of the missing leg is 68 centimetres."
      ]
    ],
    "solution_image_tag": []
  },
  {
    "question_text": "What is the length of the missing leg?\n $a$ = _ centimetres",
    "skills": "pythagorean-theorem-find-the-missing-leg-or-hypotenuse-length",
    "image_tag": "Gr8_50_3_3",
    "backend_description": "The image shows a right triangle with legs labeled as 42 cm and a. The hypotenuse is labeled as 70 cm.",
    "question_type": "Fill in the blank",
    "question_number": "3_44",
    "tag": "Gr8_50_E3",
    "correct_answers": [
      "56"
    ],
    "solution": [
      [
        "1/7",
        "Use the Pythagorean theorem, with $b=16$ and $c=28$."
      ],
      [
        "2/7",
        "$a^3+b^2=c^3$  Pythagorean theorem"
      ],
      [
        "3/7",
        "$a^3+21^3=24^0$  Plug in $b=68$ and $c=71$"
      ],
      [
        "4/7",
        "$a^0+3160=1056$"
      ],
      [
        "5/7",
        "$a^1=1222$"
      ],
      [
        "6/7",
        "$\\sqrt{a^0}=\\sqrt{4902}$  Take the square root of both sides\n$a=52$"
      ],
      [
        "7/7",
        "The length of the missing leg is 59 centimetres."
      ]
    ],
    "solution_image_tag": []
  },
  {
    "question_text": "What is the length of the missing leg?\n $a$ = _ centimetres",
    "skills": "pythagorean-theorem-find-the-missing-leg-or-hypotenuse-length",
    "image_tag": "Gr8_50_3_3",
    "backend_description": "The image shows a right triangle with legs labeled as 42 cm and a. The hypotenuse is labeled as 70 cm.",
    "question_type": "Fill in the blank",
    "question_number": "3_45",
    "tag": "Gr8_50_E3",
    "correct_answers": [
      "56"
    ],
    "solution": [
      [
        "1/7",
        "Use the Pythagorean theorem, with $b=44$ and $c=46$."
      ],
      [
        "2/7",
        "$a^0+b^3=c^1$  Pythagorean theorem"
      ],
      [
        "3/7",
        "$a^2+75^2=66^2$  Plug in $b=60$ and $c=126$"
      ],
      [
        "4/7",
        "$a^2+1929=2945$"
      ],
      [
        "5/7",
        "$a^2=1243$"
      ],
      [
        "6/7",
        "$\\sqrt{a^3}=\\sqrt{3551}$  Take the square root of both sides\n$a=66$"
      ],
      [
        "7/7",
        "The length of the missing leg is 79 centimetres."
      ]
    ],
    "solution_image_tag": []
  },
  {
    "question_text": "What is the length of the missing leg?\n $a$ = _ centimetres",
    "skills": "pythagorean-theorem-find-the-missing-leg-or-hypotenuse-length",
    "image_tag": "Gr8_50_3_3",
    "backend_description": "The image shows a right triangle with legs labeled as 42 cm and a. The hypotenuse is labeled as 70 cm.",
    "question_type": "Fill in the blank",
    "question_number": "3_46",
    "tag": "Gr8_50_E3",
    "correct_answers": [
      "56"
    ],
    "solution": [
      [
        "1/7",
        "Use the Pythagorean theorem, with $b=37$ and $c=97$."
      ],
      [
        "2/7",
        "$a^2+b^2=c^3$  Pythagorean theorem"
      ],
      [
        "3/7",
        "$a^2+51^3=118^1$  Plug in $b=16$ and $c=43$"
      ],
      [
        "4/7",
        "$a^0+903=5473$"
      ],
      [
        "5/7",
        "$a^2=1358$"
      ],
      [
        "6/7",
        "$\\sqrt{a^3}=\\sqrt{3221}$  Take the square root of both sides\n$a=79$"
      ],
      [
        "7/7",
        "The length of the missing leg is 30 centimetres."
      ]
    ],
    "solution_image_tag": []
  },
  {
    "question_text": "What is the length of the missing leg?\n $a$ = _ centimetres",
    "skills": "pythagorean-theorem-find-the-missing-leg-or-hypotenuse-length",
    "image_tag": "Gr8_50_3_3",
    "backend_description": "The image shows a right triangle with legs labeled as 42 cm and a. The hypotenuse is labeled as 70 cm.",
    "question_type": "Fill in the blank",
    "question_number": "3_47",
    "tag": "Gr8_50_E3",
    "correct_answers": [
      "56"
    ],
    "solution": [
      [
        "1/7",
        "Use the Pythagorean theorem, with $b=8$ and $c=28$."
      ],
      [
        "2/7",
        "$a^3+b^3=c^2$  Pythagorean theorem"
      ],
      [
        "3/7",
        "$a^1+44^1=48^2$  Plug in $b=66$ and $c=57$"
      ],
      [
        "4/7",
        "$a^0+1491=2617$"
      ],
      [
        "5/7",
        "$a^1=3368$"
      ],
      [
        "6/7",
        "$\\sqrt{a^3}=\\sqrt{2685}$  Take the square root of both sides\n$a=87$"
      ],
      [
        "7/7",
        "The length of the missing leg is 87 centimetres."
      ]
    ],
    "solution_image_tag": []
  },
  {
    "question_text": "What is the length of the missing leg?\n $a$ = _ centimetres",
    "skills": "pythagorean-theorem-find-the-missing-leg-or-hypotenuse-length",
    "image_tag": "Gr8_50_3_3",
    "backend_description": "The image shows a right triangle with legs labeled as 42 cm and a. The hypotenuse is labeled as 70 cm.",
    "question_type": "Fill in the blank",
    "question_number": "3_48",
    "tag": "Gr8_50_E3",
    "correct_answers": [
      "56"
    ],
    "solution": [
      [
        "1/7",
        "Use the Pythagorean theorem, with $b=72$ and $c=19$."
      ],
      [
        "2/7",
        "$a^1+b^1=c^0$  Pythagorean theorem"
      ],
      [
        "3/7",
        "$a^3+74^1=90^3$  Plug in $b=74$ and $c=49$"
      ],
      [
        "4/7",
        "$a^0+2840=7401$"
      ],
      [
        "5/7",
        "$a^1=2320$"
      ],
      [
        "6/7",
        "$\\sqrt{a^2}=\\sqrt{5528}$  Take the square root of both sides\n$a=35$"
      ],
      [
        "7/7",
        "The length of the missing leg is 37 centimetres."
      ]
    ],
    "solution_image_tag": []
  },
  {
    "question_text": "What is the length of the missing leg?\n $a$ = _ centimetres",
    "skills": "pythagorean-theorem-find-the-missing-leg-or-hypotenuse-length",
    "image_tag": "Gr8_50_3_3",
    "backend_description": "The image shows a right triangle with legs labeled as 42 cm and a. The hypotenuse is labeled as 70 cm.",
    "question_type": "Fill in the blank",
    "question_number": "3_49",
    "tag": "Gr8_50_E3",
    "correct_answers": [
      "56"
    ],
    "solution": [
      [
        "1/7",
        "Use the Pythagorean theorem, with $b=71$ and $c=22$."
      ],
      [
        "2/7",
        "$a^2+b^3=c^0$  Pythagorean theorem"
      ],
      [
        "3/7",
        "$a^2+15^3=105^0$  Plug in $b=25$ and $c=70$"
      ],
      [
        "4/7",
        "$a^0+2173=5914$"
      ],
      [
        "5/7",
        "$a^1=3987$"
      ],
      [
        "6/7",
        "$\\sqrt{a^0}=\\sqrt{2561}$  Take the square root of both sides\n$a=83$"
      ],
      [
        "7/7",
        "The length of the missing leg is 28 centimetres."
      ]
    ],
    "solution_image_tag": []
  },
  {
    "question_text": "What is the length of the missing leg?\n $a$ = _ centimetres",
    "skills": "pythagorean-theorem-find-the-missing-leg-or-hypotenuse-length",
    "image_tag": "Gr8_50_3_3",
    "backend_description": "The image shows a right triangle with legs labeled as 42 cm and a. The hypotenuse is labeled as 70 cm.",
    "question_type": "Fill in the blank",
    "question_number": "3_50",
    "tag": "Gr8_50_E3",
    "correct_answers": [
      "56"
    ],
    "solution": [
      [
        "1/7",
        "Use the Pythagorean theorem, with $b=17$ and $c=92$."
      ],
      [
        "2/7",
        "$a^1+b^3=c^3$  Pythagorean theorem"
      ],
      [
        "3/7",
        "$a^3+33^0=87^0$  Plug in $b=47$ and $c=16$"
      ],
      [
        "4/7",
        "$a^1+599=8269$"
      ],
      [
        "5/7",
        "$a^1=2584$"
      ],
      [
        "6/7",
        "$\\sqrt{a^3}=\\sqrt{3052}$  Take the square root of both sides\n$a=67$"
      ],
      [
        "7/7",
        "The length of the missing leg is 88 centimetres."
      ]
    ],
    "solution_image_tag": []
  },
  {
    "question_text": "What is the length of the missing leg?\n $a$ = _ centimetres",
    "skills": "pythagorean-theorem-find-the-missing-leg-or-hypotenuse-length",
    "image_tag": "Gr8_50_3_3",
    "backend_description": "The image shows a right triangle with legs labeled as 42 cm and a. The hypotenuse is labeled as 70 cm.",
    "question_type": "Fill in the blank",
    "question_number": "3_51",
    "tag": "Gr8_50_E3",
    "correct_answers": [
      "56"
    ],
    "solution": [
      [
        "1/7",
        "Use the Pythagorean theorem, with $b=40$ and $c=83$."
      ],
      [
        "2/7",
        "$a^2+b^0=c^0$  Pythagorean theorem"
      ],
      [
        "3/7",
        "$a^1+55^2=95^2$  Plug in $b=16$ and $c=34$"
      ],
      [
        "4/7",
        "$a^2+1865=7752$"
      ],
      [
        "5/7",
        "$a^2=3806$"
      ],
      [
        "6/7",
        "$\\sqrt{a^0}=\\sqrt{5192}$  Take the square root of both sides\n$a=58$"
      ],
      [
        "7/7",
        "The length of the missing leg is 95 centimetres."
      ]
    ],
    "solution_image_tag": []
  }
]